Metadata-Version: 2.1
Name: betterjsondb
Version: 0.1.8
Summary: A useful library for simplifying work with .json files.
Home-page: https://github.com/DarkJoij/betterjsondb
Author: Dallas
Author-email: aleksey.c5@yandex.ru
License: UNKNOWN
Platform: UNKNOWN
Classifier: Programming Language :: Python :: 3.10
Classifier: License :: OSI Approved :: MIT License
Classifier: Operating System :: OS Independent
Requires-Python: >=3.10
License-File: LICENSE
